caracara/__init__.py
caracara/client.py
caracara/common/__init__.py
caracara/common/batching.py
caracara/common/constants.py
caracara/common/csdialog.py
caracara/common/decorators.py
caracara/common/exceptions.py
caracara/common/interpolation.py
caracara/common/meta.py
caracara/common/module.py
caracara/common/pagination.py
caracara/common/policy_wrapper.py
caracara/common/sorting.py
caracara/filters/__init__.py
caracara/filters/decorators.py
caracara/modules/__init__.py
caracara/modules/custom_ioa/__init__.py
caracara/modules/custom_ioa/custom_ioa.py
caracara/modules/custom_ioa/rule_types.py
caracara/modules/custom_ioa/rules.py
caracara/modules/flight_control/__init__.py
caracara/modules/flight_control/flight_control.py
caracara/modules/hosts/__init__.py
caracara/modules/hosts/_containment.py
caracara/modules/hosts/_data_history.py
caracara/modules/hosts/_groups.py
caracara/modules/hosts/_hiding.py
caracara/modules/hosts/_online_state.py
caracara/modules/hosts/_tagging.py
caracara/modules/hosts/hosts.py
caracara/modules/prevention_policies/__init__.py
caracara/modules/prevention_policies/prevention_policies.py
caracara/modules/prevention_policies/template.py
caracara/modules/response_policies/__init__.py
caracara/modules/response_policies/response_policies.py
caracara/modules/response_policies/template.py
caracara/modules/rtr/__init__.py
caracara/modules/rtr/batch_session.py
caracara/modules/rtr/constants.py
caracara/modules/rtr/get_file.py
caracara/modules/rtr/rtr.py
caracara/modules/sensor_download/__init__.py
caracara/modules/sensor_download/sensor_download.py
caracara/modules/sensor_update_policies/__init__.py
caracara/modules/sensor_update_policies/sensor_update_policies.py
caracara/modules/users/__init__.py
caracara/modules/users/users.py
caracara-1.0.1.dist-info/LICENSE
caracara-1.0.1.dist-info/METADATA
caracara-1.0.1.dist-info/WHEEL
caracara-1.0.1.dist-info/entry_points.txt
caracara-1.0.1.dist-info/RECORD
