Metadata-Version: 2.3
Name: caracara
Version: 1.0.1
Summary: The CrowdStrike Falcon Developer Toolkit
Author: CrowdStrike
Author-email: falconpy@crowdstrike.com
Requires-Python: >=3.8.2,<4.0.0
Classifier: Programming Language :: Python :: 3
Classifier: Programming Language :: Python :: 3.9
Classifier: Programming Language :: Python :: 3.10
Classifier: Programming Language :: Python :: 3.11
Classifier: Programming Language :: Python :: 3.12
Classifier: Programming Language :: Python :: 3.13
Requires-Dist: caracara-filters (>=1.0.0,<2.0.0)
Requires-Dist: crowdstrike-falconpy (>=1.5.0,<2.0.0)
Requires-Dist: py7zr (>=0.22.0,<0.23.0)
Requires-Dist: tqdm (>=4.67.1,<5.0.0)
